april_asr/__init__.py
april_asr/_april.py
april_asr/_april_c_ffi.py
april_asr/example.py
april_asr/libaprilasr.dll
april_asr/onnxruntime.dll
april_asr-0.0.4.dist-info/METADATA
april_asr-0.0.4.dist-info/WHEEL
april_asr-0.0.4.dist-info/entry_points.txt
april_asr-0.0.4.dist-info/top_level.txt
april_asr-0.0.4.dist-info/RECORD
